solo/VERSION
solo/__init__.py
solo/client.py
solo/commands.py
solo/dfu.py
solo/enums.py
solo/exceptions.py
solo/helpers.py
solo/hmac_secret.py
solo/operations.py
solo/solotool.py
solo/cli/__init__.py
solo/cli/_checks.py
solo/cli/key.py
solo/cli/monitor.py
solo/cli/program.py
solo/cli/update.py
solo/devices/__init__.py
solo/devices/base.py
solo/devices/solo_v1.py
solo/fido2/__init__.py
onlykey_solo_python-0.0.32.dist-info/entry_points.txt
onlykey_solo_python-0.0.32.dist-info/LICENSE-APACHE
onlykey_solo_python-0.0.32.dist-info/LICENSE-MIT
onlykey_solo_python-0.0.32.dist-info/WHEEL
onlykey_solo_python-0.0.32.dist-info/METADATA
onlykey_solo_python-0.0.32.dist-info/RECORD
